plone.schemaeditor-4.0.13-py3.13-nspkg.pth
plone/schemaeditor/__init__.py
plone/schemaeditor/configure.zcml
plone/schemaeditor/fields.py
plone/schemaeditor/fields.zcml
plone/schemaeditor/interfaces.py
plone/schemaeditor/schema.py
plone/schemaeditor/schema.zcml
plone/schemaeditor/testing.py
plone/schemaeditor/utils.py
plone/schemaeditor/vocabularies.py
plone/schemaeditor/browser/__init__.py
plone/schemaeditor/browser/configure.zcml
plone/schemaeditor/browser/field/__init__.py
plone/schemaeditor/browser/field/configure.zcml
plone/schemaeditor/browser/field/edit.pt
plone/schemaeditor/browser/field/edit.py
plone/schemaeditor/browser/field/fieldset.py
plone/schemaeditor/browser/field/order.py
plone/schemaeditor/browser/field/traversal.py
plone/schemaeditor/browser/schema/__init__.py
plone/schemaeditor/browser/schema/add.pt
plone/schemaeditor/browser/schema/add_field.py
plone/schemaeditor/browser/schema/add_fieldset.py
plone/schemaeditor/browser/schema/configure.zcml
plone/schemaeditor/browser/schema/delete_fieldset.py
plone/schemaeditor/browser/schema/listing.py
plone/schemaeditor/browser/schema/schema_listing.pt
plone/schemaeditor/browser/schema/traversal.py
plone/schemaeditor/tests/__init__.py
plone/schemaeditor/tests/browser_testing.zcml
plone/schemaeditor/tests/choice.rst
plone/schemaeditor/tests/editing.rst
plone/schemaeditor/tests/extending.rst
plone/schemaeditor/tests/field_schemata.rst
plone/schemaeditor/tests/fixtures.py
plone/schemaeditor/tests/layout.pt
plone/schemaeditor/tests/minmax.rst
plone/schemaeditor/tests/robot_testing.zcml
plone/schemaeditor/tests/test_fields.py
plone/schemaeditor/tests/test_robot.py
plone/schemaeditor/tests/tests.py
plone/schemaeditor/tests/robot/test_fields.robot
plone_schemaeditor-4.0.13.dist-info/METADATA
plone_schemaeditor-4.0.13.dist-info/WHEEL
plone_schemaeditor-4.0.13.dist-info/namespace_packages.txt
plone_schemaeditor-4.0.13.dist-info/top_level.txt
plone_schemaeditor-4.0.13.dist-info/RECORD
