Metadata-Version: 2.4
Name: plone.schemaeditor
Version: 4.0.13
Summary: Provides through-the-web editing of a zope schema/interface.
Home-page: https://github.com/plone/plone.schemaeditor
Author: David Glick
Author-email: dglick@gmail.com
License: BSD
Keywords: plone schema ttw
Classifier: Development Status :: 6 - Mature
Classifier: Framework :: Zope
Classifier: Framework :: Zope :: 5
Classifier: Framework :: Plone
Classifier: Framework :: Plone :: Core
Classifier: Framework :: Plone :: 6.0
Classifier: Programming Language :: Python
Classifier: Programming Language :: Python :: 3.8
Classifier: Programming Language :: Python :: 3.9
Classifier: Programming Language :: Python :: 3.10
Classifier: Programming Language :: Python :: 3.11
Classifier: Topic :: Software Development :: Libraries :: Python Modules
Classifier: License :: OSI Approved :: BSD License
Requires-Python: >=3.8
Requires-Dist: Acquisition
Requires-Dist: Products.statusmessages
Requires-Dist: Zope
Requires-Dist: plone.memoize
Requires-Dist: plone.protect
Requires-Dist: plone.supermodel
Requires-Dist: setuptools
Requires-Dist: zope.cachedescriptors
Requires-Dist: zope.component
Requires-Dist: zope.container
Requires-Dist: zope.event
Requires-Dist: zope.globalrequest
Requires-Dist: zope.i18n
Requires-Dist: zope.i18nmessageid
Requires-Dist: zope.interface
Requires-Dist: zope.lifecycleevent
Requires-Dist: zope.schema
Requires-Dist: zope.security
Requires-Dist: zope.publisher
Requires-Dist: z3c.form
Requires-Dist: plone.z3cform
Requires-Dist: plone.autoform
Provides-Extra: test
Requires-Dist: six; extra == "test"
Requires-Dist: Products.Genericsetup; extra == "test"
Requires-Dist: plone.app.testing; extra == "test"
Requires-Dist: plone.app.robotframework; extra == "test"
Requires-Dist: plone.keyring; extra == "test"
Requires-Dist: plone.supermodel; extra == "test"
Requires-Dist: plone.testing; extra == "test"
Requires-Dist: robotsuite; extra == "test"
Requires-Dist: transaction; extra == "test"
Dynamic: author
Dynamic: author-email
Dynamic: classifier
Dynamic: description
Dynamic: description-content-type
Dynamic: home-page
Dynamic: keywords
Dynamic: license
Dynamic: provides-extra
Dynamic: requires-dist
Dynamic: requires-python
Dynamic: summary
